PySuiteCRM/SuiteCRM.py
PySuiteCRM/__init__.py
PySuiteCRM-2022.8.13.dist-info/LICENSE
PySuiteCRM-2022.8.13.dist-info/METADATA
PySuiteCRM-2022.8.13.dist-info/WHEEL
PySuiteCRM-2022.8.13.dist-info/top_level.txt
PySuiteCRM-2022.8.13.dist-info/RECORD
