Metadata-Version: 2.1
Name: PySuiteCRM
Version: 2022.8.13
Summary: Python client for SuiteCRM v8 API
Home-page: https://github.com/RussellJuma/PySuiteCRM
Author: Russell Juma
Author-email: RussellJuma@gmail.com
Project-URL: Bug Tracker, https://github.com/RussellJuma/PySuiteCRM/issues
Classifier: Programming Language :: Python :: 3
Classifier: License :: OSI Approved :: MIT License
Classifier: Operating System :: OS Independent
Requires-Python: >=3.6
License-File: LICENSE
